pvw/__init_.py
pvw/args_parser.py
pvw/config.py
pvw/env.py
pvw/main.py
pvw/shell_executor.py
pvw/template.py
pvw-0.0.8.data/scripts/pvw
pvw-0.0.8.data/scripts/pvw.ps1
tests/test_install_wrapper.py
tests/tests.py
pvw-0.0.8.dist-info/METADATA
pvw-0.0.8.dist-info/WHEEL
pvw-0.0.8.dist-info/entry_points.txt
pvw-0.0.8.dist-info/top_level.txt
pvw-0.0.8.dist-info/RECORD
