Metadata-Version: 2.1
Name: pvw
Version: 0.0.8
Summary: a lightweight python venv wrapper to manage venvs
Author-email: Hagemon <ooonefolder@gmail.com>
License: MIT
Project-URL: Homepage, https://github.com/hagemon/pvw
Project-URL: Repository, https://github.com/hagemon/pvw
Project-URL: Documentation, https://github.com/hagemon/pvw
Keywords: venv,virtual env,python
Classifier: Programming Language :: Python :: 3
Requires-Python: >=3.6
Requires-Dist: termcolor
Requires-Dist: click
Requires-Dist: importlib-metadata ; python_version > "3.6"
